antismash_models/__init__.py
antismash_models/base.py
antismash_models/control.py
antismash_models/job.py
antismash_models/notice.py
antismash_models/py.typed
antismash_models/utils.py
antismash_models-0.1.26.dist-info/LICENSE.txt
antismash_models-0.1.26.dist-info/METADATA
antismash_models-0.1.26.dist-info/WHEEL
antismash_models-0.1.26.dist-info/top_level.txt
antismash_models-0.1.26.dist-info/RECORD
