Metadata-Version: 2.1
Name: antismash-models
Version: 0.1.26
Summary: An object model for mapping antiSMASH data objects from and to Redis via aioredis.
Home-page: https://github.com/antismash/models/
Author: Kai Blin
Author-email: kblin@biosustain.dtu.dk
License: GNU Affero General Public License v3 or later (AGPLv3+)
Classifier: Programming Language :: Python
Classifier: Development Status :: 3 - Alpha
Classifier: Intended Audience :: Science/Research
Classifier: Topic :: Scientific/Engineering :: Bio-Informatics
Classifier: License :: OSI Approved :: GNU Affero General Public License v3 or later (AGPLv3+)
Classifier: Operating System :: OS Independent
License-File: LICENSE.txt
Requires-Dist: redis
Provides-Extra: testing
Requires-Dist: pytest ; extra == 'testing'
Requires-Dist: coverage ; extra == 'testing'
Requires-Dist: pytest-cov ; extra == 'testing'
Requires-Dist: fakeredis ; extra == 'testing'
Requires-Dist: pytest-asyncio ; extra == 'testing'
Requires-Dist: flake8 ; extra == 'testing'
Requires-Dist: mypy ; extra == 'testing'
Requires-Dist: types-redis ; extra == 'testing'
